golem-port-checker.service
port_checker/main.py
golem_port_checker-0.1.25.dist-info/METADATA
golem_port_checker-0.1.25.dist-info/WHEEL
golem_port_checker-0.1.25.dist-info/entry_points.txt
golem_port_checker-0.1.25.dist-info/RECORD
