Metadata-Version: 2.3
Name: golem-port-checker
Version: 0.1.25
Summary: Port checking service for VM on Golem - Verify network connectivity for Golem providers
Keywords: golem,network,port-checker,connectivity,verification
Author: Phillip Jensen
Author-email: phillip+vm-on-golem@golemgrid.com
Requires-Python: >=3.9
Classifier: Development Status :: 4 - Beta
Classifier: Environment :: Web Environment
Classifier: Framework :: FastAPI
Classifier: Intended Audience :: System Administrators
Classifier: Operating System :: OS Independent
Classifier: Programming Language :: Python :: 3
Classifier: Programming Language :: Python :: 3.9
Classifier: Programming Language :: Python :: 3.10
Classifier: Programming Language :: Python :: 3.11
Classifier: Programming Language :: Python :: 3.12
Classifier: Programming Language :: Python :: 3.13
Classifier: Topic :: Internet :: WWW/HTTP :: HTTP Servers
Classifier: Topic :: System :: Networking :: Monitoring
Requires-Dist: aiohttp (>=3.8.1,<4.0.0)
Requires-Dist: asyncio (>=3.4.3,<4.0.0)
Requires-Dist: colorlog (>=6.8.0,<7.0.0)
Requires-Dist: fastapi (>=0.68.0,<0.69.0)
Requires-Dist: pydantic (>=1.8.2,<2.0.0)
Requires-Dist: python-dotenv (>=1.0.0,<2.0.0)
Requires-Dist: uvicorn (>=0.15.0,<0.16.0)
Project-URL: Homepage, https://github.com/cryptobench/vm-on-golem
Project-URL: Repository, https://github.com/cryptobench/vm-on-golem
